{
  "button_cancel": "Cancel",
  "button_create": "Add",
  "button_edit": "Save",
  "button_reset": "Initial value",
  "label_select-validation-type": "Валидация значений",
  "label_select-validation-type-default": "По умолчанию",
  "label_select-validation-type-default-hint": "Цифры, буквы и безопасные символы",
  "label_select-validation-type-regex": "Регулярное выражение",
  "label_switch-template": "Разрешить использовать в настройке источника",
  "label_switch-template-warn": "Параметр будет создан, но его нельзя будет использовать в источнике",
  "label_textarea-regex-placeholder": "Регулярное выражение на Python",
  "parameter_default-value": "Default value",
  "parameter_name": "Name",
  "parameter_name-note": "Parameter name restrictions: \n* Lowercase Latin letters, digits, hyphens, and underscores are acceptable. The first character can't be an underscore: `_name`. \n* Parameter name length should not exceed 36 characters. \n* Reserved parameter names that cannot be used: `tab`, `state`, `mode`, `focus`, `grid`, `tz`, `from`, `to`.",
  "parameter_type": "Type",
  "title_create-parameter": "Add parameter",
  "title_edit-parameter": "Edit parameter"
}
