{
  "action_assign-role": "Assign role",
  "action_change-password": "Change password",
  "action_delete-user": "Delete user",
  "action_edit-profile": "Edit account",
  "label_email": "Email",
  "label_failed-to-load-user": "An error occurred while loading the account. The user may have been deleted",
  "label_first-name": "First name",
  "label_last-name": "Last name",
  "label_login": "Login",
  "label_role": "Role",
  "label_user-id": "ID",
  "title_administration": "Administration",
  "title_permissions": "Permissions",
  "title_profile": "Account"
}
